{
  "version": "WEBUS",
  "book": "MIC",
  "chapter": 7,
  "verses": [
    {
      "verse": "1",
      "text": "Misery is mine!"
    },
    {
      "verse": "2",
      "text": "The godly man has perished out of the earth,"
    },
    {
      "verse": "3",
      "text": "Their hands are on that which is evil to do it diligently."
    },
    {
      "verse": "4",
      "text": "The best of them is like a brier."
    },
    {
      "verse": "5",
      "text": "Don’t trust in a neighbor."
    },
    {
      "verse": "6",
      "text": "For the son dishonors the father,"
    },
    {
      "verse": "7",
      "text": "But as for me, I will look to Yahweh."
    },
    {
      "verse": "8",
      "text": "Don’t rejoice against me, my enemy."
    },
    {
      "verse": "9",
      "text": "I will bear the indignation of Yahweh,"
    },
    {
      "verse": "10",
      "text": "Then my enemy will see it,"
    },
    {
      "verse": "11",
      "text": "A day to build your walls!"
    },
    {
      "verse": "12",
      "text": "In that day they will come to you from Assyria and the cities of Egypt,"
    },
    {
      "verse": "13",
      "text": "Yet the land will be desolate because of those who dwell therein,"
    },
    {
      "verse": "14",
      "text": "Shepherd your people with your staff,"
    },
    {
      "verse": "15",
      "text": "“As in the days of your coming out of the land of Egypt,"
    },
    {
      "verse": "16",
      "text": "The nations will see and be ashamed of all their might."
    },
    {
      "verse": "17",
      "text": "They will lick the dust like a serpent."
    },
    {
      "verse": "18",
      "text": "Who is a God like you, who pardons iniquity,"
    },
    {
      "verse": "19",
      "text": "He will again have compassion on us."
    },
    {
      "verse": "20",
      "text": "You will give truth to Jacob,"
    }
  ]
}