{
  "version": "WEBUS",
  "book": "PSA",
  "chapter": 66,
  "verses": [
    {
      "verse": "1",
      "text": "Make a joyful shout to God, all the earth!"
    },
    {
      "verse": "2",
      "text": "Sing to the glory of his name!"
    },
    {
      "verse": "3",
      "text": "Tell God, “How awesome are your deeds!"
    },
    {
      "verse": "4",
      "text": "All the earth will worship you,"
    },
    {
      "verse": "5",
      "text": "Come, and see God’s deeds—"
    },
    {
      "verse": "6",
      "text": "He turned the sea into dry land."
    },
    {
      "verse": "7",
      "text": "He rules by his might forever."
    },
    {
      "verse": "8",
      "text": "Praise our God, you peoples!"
    },
    {
      "verse": "9",
      "text": "who preserves our life among the living,"
    },
    {
      "verse": "10",
      "text": "For you, God, have tested us."
    },
    {
      "verse": "11",
      "text": "You brought us into prison."
    },
    {
      "verse": "12",
      "text": "You allowed men to ride over our heads."
    },
    {
      "verse": "13",
      "text": "I will come into your temple with burnt offerings."
    },
    {
      "verse": "14",
      "text": "which my lips promised,"
    },
    {
      "verse": "15",
      "text": "I will offer to you burnt offerings of fat animals,"
    },
    {
      "verse": "16",
      "text": "Come and hear, all you who fear God."
    },
    {
      "verse": "17",
      "text": "I cried to him with my mouth."
    },
    {
      "verse": "18",
      "text": "If I cherished sin in my heart,"
    },
    {
      "verse": "19",
      "text": "But most certainly, God has listened."
    },
    {
      "verse": "20",
      "text": "Blessed be God, who has not turned away my prayer,"
    }
  ]
}