{
  "version": "KJV",
  "book": "PSA",
  "chapter": 66,
  "verses": [
    {
      "verse": "1",
      "text": "Make a joyful noise unto God, all ye lands:"
    },
    {
      "verse": "2",
      "text": "Sing forth the honour of his name: Make his praise glorious."
    },
    {
      "verse": "3",
      "text": "Say unto God, How terrible art thou in thy works!"
    },
    {
      "verse": "4",
      "text": "All the earth shall worship thee,"
    },
    {
      "verse": "5",
      "text": "Come and see the works of God:"
    },
    {
      "verse": "6",
      "text": "He turned the sea into dry land:"
    },
    {
      "verse": "7",
      "text": "He ruleth by his power for ever; His eyes behold the nations:"
    },
    {
      "verse": "8",
      "text": "O bless our God, ye people,"
    },
    {
      "verse": "9",
      "text": "Which holdeth our soul in life,"
    },
    {
      "verse": "10",
      "text": "For thou, O God, hast proved us:"
    },
    {
      "verse": "11",
      "text": "Thou broughtest us into the net;"
    },
    {
      "verse": "12",
      "text": "Thou hast caused men to ride over our heads;"
    },
    {
      "verse": "13",
      "text": "I will go into thy house with burnt offerings:"
    },
    {
      "verse": "14",
      "text": "which my lips have uttered, and my mouth hath spoken, when I was in trouble."
    },
    {
      "verse": "15",
      "text": "I will offer unto thee burnt sacrifices of fatlings, with the incense of rams;"
    },
    {
      "verse": "16",
      "text": "Come and hear, all ye that fear God,"
    },
    {
      "verse": "17",
      "text": "I cried unto him with my mouth,"
    },
    {
      "verse": "18",
      "text": "If I regard iniquity in my heart,"
    },
    {
      "verse": "19",
      "text": " But verily God hath heard me ;"
    },
    {
      "verse": "20",
      "text": "Blessed be God, which hath not turned away my prayer,"
    }
  ]
}